libname/__init__.py
libname/money_calculator.py
moneyvaluemak-0.0.1.dist-info/METADATA
moneyvaluemak-0.0.1.dist-info/WHEEL
moneyvaluemak-0.0.1.dist-info/top_level.txt
moneyvaluemak-0.0.1.dist-info/RECORD
