Metadata-Version: 2.1
Name: moneyvaluemak
Version: 0.0.1
Summary: For Translate Money Number to Words
Author: SagarMak
Author-email: sagar.makwana@crestdatasys.com
Keywords: python,money
Classifier: Development Status :: 1 - Planning
Classifier: Intended Audience :: Developers
Classifier: Programming Language :: Python :: 3
Classifier: Operating System :: Unix
Classifier: Operating System :: MacOS :: MacOS X
Classifier: Operating System :: Microsoft :: Windows
